strainge/variant_caller.py
strainge/sample_compare.py
strainge/search_tool.py
strainge/_version.py
strainge/__init__.py
strainge/kmerizer.cpython-39-darwin.so
strainge/comparison.py
strainge/utils.py
strainge/cluster.py
strainge/kmertools.py
strainge/io/variants.py
strainge/io/comparisons.py
strainge/io/__init__.py
strainge/io/utils.py
strainge/cli/registry.py
strainge/cli/straingr.py
strainge/cli/straingst.py
strainge/cli/__init__.py
strainge/cli/kmersets.py
strainge/cli/main.py
strainge-1.3.9.data/scripts/kmertree
strainge-1.3.9.data/scripts/kmerseq
strainge-1.3.9.data/scripts/kmercoverage
strainge-1.3.9.data/scripts/kmerspectrum
strainge-1.3.9.data/scripts/treepath
strainge-1.3.9.data/scripts/kmersimilarity
strainge-1.3.9.data/scripts/refseq-download
strainge-1.3.9.data/scripts/pankmer
strainge-1.3.9.data/scripts/refseq-extract
strainge-1.3.9.dist-info/RECORD
strainge-1.3.9.dist-info/LICENSE
strainge-1.3.9.dist-info/WHEEL
strainge-1.3.9.dist-info/entry_points.txt
strainge-1.3.9.dist-info/top_level.txt
strainge-1.3.9.dist-info/METADATA
