Metadata-Version: 2.1
Name: strainge
Version: 1.3.9
Summary: Strain Genome Explorer: a tool suite for tracking and characterizing low-abundance strains.
Author: Bruce Walker, Tim Straub, Lucas van Dijk
Author-email: bruce@broadinstitute.org, tstraub@broadinstitute.org, lvandijk@broadinstitute.org
Classifier: Programming Language :: Python :: 3
Classifier: License :: OSI Approved :: BSD License
Classifier: Operating System :: OS Independent
Classifier: Environment :: Console
Classifier: Topic :: Scientific/Engineering :: Bio-Informatics
Requires-Python: >=3.8
License-File: LICENSE
Requires-Dist: numpy
Requires-Dist: scipy
Requires-Dist: h5py
Requires-Dist: intervaltree
Requires-Dist: matplotlib
Requires-Dist: scikit-bio >=0.5.8
Requires-Dist: scikit-learn >=0.24
Requires-Dist: pysam
